pytorch_quant_tool/__init__.py
pytorch_quant_tool/util.py
pytorch_quant_tool/rules/__init__.py
pytorch_quant_tool/rules/convbn.py
pytorch_quant_tool/rules/downsample.py
pytorch_quant_tool/rules/fuse_rule.py
pytorch_quant_tool-1.3.1.dist-info/LICENSE
pytorch_quant_tool-1.3.1.dist-info/METADATA
pytorch_quant_tool-1.3.1.dist-info/WHEEL
pytorch_quant_tool-1.3.1.dist-info/top_level.txt
pytorch_quant_tool-1.3.1.dist-info/RECORD
