Metadata-Version: 2.1
Name: pytorch-quant-tool
Version: 1.3.1
Summary: An experimental neural network quantization environment in Pytorch.
Home-page: https://github.com/neolinsu/pytorch_quant_tool
Author: Jiazhen Lin
Author-email: neolunsu@gmail.com
License: MIT
Platform: UNKNOWN
Classifier: Development Status :: 1 - Planning
Classifier: License :: OSI Approved :: MIT License
Classifier: Topic :: Scientific/Engineering :: Artificial Intelligence
Classifier: Topic :: Software Development :: Libraries :: Python Modules
Classifier: Programming Language :: Python
Classifier: Programming Language :: Python :: 3.6
Classifier: Programming Language :: Python :: 3.7
Classifier: Programming Language :: Python :: Implementation :: CPython
Requires-Dist: pytorch (==1.3.1)
